tracktable_data/__init__.py
tracktable_data/data.py
tracktable_data/internal_test_data/__init__.py
tracktable_data/internal_test_data/trajectory.json
tracktable_data/internal_test_data/Points/Points1000.csv
tracktable_data/internal_test_data/Points/PointsWithComments.csv
tracktable_data/internal_test_data/Points/PointsWithSkippableHeaders.csv
tracktable_data/internal_test_data/Points/SampleASDI.csv
tracktable_data/internal_test_data/Points/SampleFlightsUS.csv
tracktable_data/internal_test_data/Points/SampleHeatmapPoints.csv
tracktable_data/internal_test_data/Points/SampleNFlights.csv
tracktable_data/internal_test_data/Points/SamplePointsCartesian.csv
tracktable_data/internal_test_data/Points/SampleTrajectories.csv
tracktable_data/internal_test_data/Points/ads_with_utf8.csv
tracktable_data/internal_test_data/Points/tab_separated/SampleFlightsUS.tsv
tracktable_data/internal_test_data/Points/tab_separated/SampleHeatmapPoints.tsv
tracktable_data/internal_test_data/Timestamps/PointsWithTimestamps1.csv
tracktable_data/internal_test_data/Timestamps/PointsWithTimestamps2.csv
tracktable_data/internal_test_data/Timestamps/PointsWithTimestamps3.csv
tracktable_data/internal_test_data/Trajectories/NYHarbor_2020_06_30_first_hour.traj
tracktable_data/python_example_data/NYHarbor_2020_06_30_first_hour.csv
tracktable_data/python_example_data/NYHarbor_2020_12_08.traj
tracktable_data/python_example_data/NYHarbor_2020_12_first_week.traj
tracktable_data/python_example_data/SampleFlight.csv
tracktable_data/python_example_data/SampleFlightsUS.csv
tracktable_data/python_example_data/SampleTrajectories.csv
tracktable_data/python_example_data/SampleTrajectories.traj
tracktable_data/python_example_data/TwoSampleFlights.csv
tracktable_data/python_example_data/US_coastal_2020_06_30.traj
tracktable_data/python_example_data/VirginiaBeach_2020_06_04_to_06_filtered.traj
tracktable_data/python_example_data/__init__.py
tracktable_data/python_example_data/one_prediction.traj
tracktable_data-1.7.3.1.dist-info/licenses/LICENSE.html
tracktable_data-1.7.3.1.dist-info/licenses/LICENSE.txt
tracktable_data-1.7.3.1.dist-info/METADATA
tracktable_data-1.7.3.1.dist-info/WHEEL
tracktable_data-1.7.3.1.dist-info/top_level.txt
tracktable_data-1.7.3.1.dist-info/RECORD
