Metadata-Version: 2.4
Name: tracktable-data
Version: 1.7.3.1
Summary: Supplemental data files for Tracktable
Author: Danny Rintoul, Chris Valicka, Ben Newton, Paul Schrum, Kat Ward, Rick Vinyard, Michael Scoggin, Geoff Danielson, Michael Fadem, Diana He
Author-email: Andy Wilson <atwilso@sandia.gov>, Phil Baxley <pabaxle@sandia.gov>
License-Expression: BSD-2-Clause
Project-URL: Repository, https://github.com/sandialabs/tracktable-data
Project-URL: Issues, https://github.com/sandialabs/tracktable-data/issues
Classifier: Programming Language :: Python :: 3
Classifier: Programming Language :: Python :: 3.9
Classifier: Programming Language :: Python :: 3.10
Classifier: Programming Language :: Python :: 3.11
Classifier: Programming Language :: Python :: 3.12
Classifier: Programming Language :: Python :: 3.13
Classifier: Development Status :: 5 - Production/Stable
Classifier: Intended Audience :: Developers
Classifier: Natural Language :: English
Classifier: Operating System :: OS Independent
Requires-Python: >=3.9
License-File: LICENSE.txt
License-File: LICENSE.html
Dynamic: license-file
